soundscan/__init__.py
soundscan/audio_processor.py
soundscan/cli.py
soundscan/config.py
soundscan/downloader.py
soundscan/history_manager.py
soundscan/recognizer.py
soundscan/super_shazam.py
soundscan-1.0.1.dist-info/METADATA
soundscan-1.0.1.dist-info/WHEEL
soundscan-1.0.1.dist-info/entry_points.txt
soundscan-1.0.1.dist-info/top_level.txt
soundscan-1.0.1.dist-info/RECORD
