Metadata-Version: 2.4
Name: soundscan
Version: 1.0.1
Summary: CLI toolkit for searching, recognizing and downloading music.
Home-page: https://pypi.org/project/soundscan/
Author: wambua
Author-email: swskye17@gmail.com
License: GNU v3
Keywords: soundscan,shazam,music_downloader
Classifier: Environment :: Console
Classifier: Natural Language :: English
Classifier: Operating System :: OS Independent
Classifier: Programming Language :: Python
Classifier: Programming Language :: Python :: 3 :: Only
Classifier: Programming Language :: Python :: 3.12
Classifier: Programming Language :: Python :: 3.13
Requires-Python: >=3.12
Requires-Dist: setuptools
Requires-Dist: wheel
Requires-Dist: argparse
Requires-Dist: yt_dlp
Dynamic: author
Dynamic: author-email
Dynamic: classifier
Dynamic: description
Dynamic: description-content-type
Dynamic: home-page
Dynamic: keywords
Dynamic: license
Dynamic: requires-dist
Dynamic: requires-python
Dynamic: summary
